edgegap_api/__init__.py
edgegap_api/_configuration.py
edgegap_api/_helper.py
edgegap_api-1.9.12.dist-info/LICENSE
edgegap_api-1.9.12.dist-info/METADATA
edgegap_api-1.9.12.dist-info/WHEEL
edgegap_api-1.9.12.dist-info/RECORD
