Metadata-Version: 2.1
Name: edgegap-api
Version: 1.9.12
Summary: The Edgegap API library includes various tools and helpers for interacting with RESTful and other types of APIs. It is designed for use within the Edgegap organization.
Author: Bastien Roy
Author-email: bastien@edgegap.com
Requires-Python: >=3.10,<4.0
Classifier: Programming Language :: Python :: 3
Classifier: Programming Language :: Python :: 3.10
Classifier: Programming Language :: Python :: 3.11
Classifier: Programming Language :: Python :: 3.12
Requires-Dist: aiohttp[speedups] (>=3.9.5,<4.0.0)
Requires-Dist: pydantic (>=2.7.1,<3.0.0)
Requires-Dist: pytimeparse (>=1.1.8,<2.0.0)
